{
  "updated": "2026-04-20T11:33:53.278Z",
  "source": "pinnacle-football-live-arcadia",
  "total": 6,
  "matches": [
    {
      "eventId": "1628920222",
      "home": "Dnepr Mogilev",
      "away": "Torpedo Zhodino",
      "league": "Belarus - Premier League",
      "sport": "football",
      "elapsed": 23,
      "status": "started",
      "score": "1-0",
      "link": "",
      "p1": 1.249,
      "x": 5.52,
      "p2": 12.28,
      "time": "2026-04-20T11:00:00Z"
    },
    {
      "eventId": "1628910295",
      "home": "Hong Kong Rangers FC",
      "away": "Kowloon City",
      "league": "Hong Kong - U22 League",
      "sport": "football",
      "elapsed": 38,
      "status": "started",
      "score": "0-0",
      "link": "",
      "p1": 1.061,
      "x": 8.97,
      "p2": 25.94,
      "time": "2026-04-20T10:45:00Z"
    },
    {
      "eventId": "1628910290",
      "home": "Olimpia Asuncion",
      "away": "Cerro Porteno",
      "league": "Paraguay - Reserve League",
      "sport": "football",
      "elapsed": 6,
      "status": "started",
      "score": "1-0",
      "link": "",
      "p1": 1.361,
      "x": 3.96,
      "p2": 7.7,
      "time": "2026-04-20T10:30:00Z"
    },
    {
      "eventId": "1628910291",
      "home": "Sportivo Ameliano",
      "away": "Nacional Asuncion",
      "league": "Paraguay - Reserve League",
      "sport": "football",
      "elapsed": 8,
      "status": "started",
      "score": "1-0",
      "link": "",
      "p1": 1.581,
      "x": 3.34,
      "p2": 5.39,
      "time": "2026-04-20T10:30:00Z"
    },
    {
      "eventId": "1628877583",
      "home": "Sheffield Wednesday",
      "away": "Crewe Alexandra",
      "league": "England - Professional Development League U21",
      "sport": "football",
      "elapsed": 23,
      "status": "started",
      "score": "2-0",
      "link": "",
      "p1": null,
      "x": null,
      "p2": null,
      "time": "2026-04-20T11:00:00Z"
    },
    {
      "eventId": "1628864860",
      "home": "Oleksandria",
      "away": "Veres Rivne",
      "league": "Ukraine - Premier League",
      "sport": "football",
      "elapsed": 19,
      "status": "started",
      "score": "0-2",
      "link": "",
      "p1": null,
      "x": null,
      "p2": null,
      "time": "2026-04-20T10:00:00Z"
    }
  ]
}